morse/__init__.py
morse/decoder.py
morse/encoder.py
morse/morse.py
morse/py.typed
morse_pro-0.1.2.dist-info/licenses/LICENSE
morse_pro-0.1.2.dist-info/METADATA
morse_pro-0.1.2.dist-info/WHEEL
morse_pro-0.1.2.dist-info/entry_points.txt
morse_pro-0.1.2.dist-info/top_level.txt
morse_pro-0.1.2.dist-info/RECORD
