Metadata-Version: 2.4
Name: morse_pro
Version: 0.1.2
Summary: Encode and decode Morse code messages
Home-page: https://github.com/ChrstphrChevalier/100DaysOfCode-Python/tree/main/04_Professionnal__(Days82_to_Day100)/Day82__Morse_Pro
Author: Chrstphr CHEVALIER
Author-email: chrstphr.chevalier@gmail.com
Project-URL: Bug Tracker, https://github.com/ChrstphrChevalier/100DaysOfCode-Python/issues
Classifier: Programming Language :: Python :: 3
Classifier: License :: OSI Approved :: MIT License
Classifier: Operating System :: OS Independent
Classifier: Typing :: Typed
Requires-Python: >=3.6
License-File: LICENSE
Dynamic: author
Dynamic: author-email
Dynamic: classifier
Dynamic: description
Dynamic: description-content-type
Dynamic: home-page
Dynamic: license-file
Dynamic: project-url
Dynamic: requires-python
Dynamic: summary
